{
  "runId": "dump_213302",
  "createdAt": "2026-07-09T19:34:56.946877Z",
  "opportunities": [
    {
      "id": "opp-0",
      "startupName": "ONLIVE LTD",
      "goliathScore": 60.0,
      "status": "warming",
      "confidence": 0.55,
      "riskLevel": "medium",
      "scoreReason": "Strong traction signals in AI.",
      "prediction": "ONLIVE LTD is positioned to raise within 9 months.",
      "sector": "AI",
      "location": "Barcelona",
      "stage": null,
      "evidence": [
        {
          "id": "evd-974b7256",
          "source": "web",
          "title": "[PDF] Barcelona-&-Catalonia-Startup-Hub-2025 vdef a 260225_ENG",
          "url": "https://catalonia.com/documents/176177/179363/catalonia-trade-and-investment-analysis-of-the-startup-ecosystem-in-catalonia.pdf",
          "snippet": null
        },
        {
          "id": "evd-b5235824",
          "source": "web",
          "title": "The Barcelona Startup Ecosystem - Digital, Tech, and Open Innovation - Mind the Bridge",
          "url": "https://mindthebridge.com/2023-scaleups-barcelona",
          "snippet": null
        }
      ],
      "summary": "Ai in barcelona"
    },
    {
      "id": "opp-1",
      "startupName": "RISC-V International",
      "goliathScore": 60.0,
      "status": "warming",
      "confidence": 0.55,
      "riskLevel": "medium",
      "scoreReason": "Strong traction signals in AI.",
      "prediction": "RISC-V International is positioned to raise within 9 months.",
      "sector": "AI",
      "location": "Barcelona",
      "stage": null,
      "evidence": [
        {
          "id": "evd-c14414ec",
          "source": "web",
          "title": "[PDF] Barcelona-&-Catalonia-Startup-Hub-2025 vdef a 260225_ENG",
          "url": "https://catalonia.com/documents/176177/179363/catalonia-trade-and-investment-analysis-of-the-startup-ecosystem-in-catalonia.pdf",
          "snippet": null
        },
        {
          "id": "evd-1ea88843",
          "source": "web",
          "title": "The Barcelona Startup Ecosystem - Digital, Tech, and Open Innovation - Mind the Bridge",
          "url": "https://mindthebridge.com/2023-scaleups-barcelona",
          "snippet": null
        }
      ],
      "summary": "Ai in barcelona"
    },
    {
      "id": "opp-2",
      "startupName": "Submer",
      "goliathScore": 60.0,
      "status": "warming",
      "confidence": 0.55,
      "riskLevel": "medium",
      "scoreReason": "Strong traction signals in AI.",
      "prediction": "Submer is positioned to raise within 9 months.",
      "sector": "AI",
      "location": "Barcelona",
      "stage": null,
      "evidence": [
        {
          "id": "evd-0c1f3113",
          "source": "web",
          "title": "[PDF] Barcelona-&-Catalonia-Startup-Hub-2025 vdef a 260225_ENG",
          "url": "https://catalonia.com/documents/176177/179363/catalonia-trade-and-investment-analysis-of-the-startup-ecosystem-in-catalonia.pdf",
          "snippet": null
        },
        {
          "id": "evd-e9df4f3e",
          "source": "web",
          "title": "The Barcelona Startup Ecosystem - Digital, Tech, and Open Innovation - Mind the Bridge",
          "url": "https://mindthebridge.com/2023-scaleups-barcelona",
          "snippet": null
        }
      ],
      "summary": "Ai in barcelona"
    },
    {
      "id": "opp-3",
      "startupName": "BARCELONA SUPERCOMPUTING CENTER - CENTRO NACIONAL DE SUPERCOMPUTACIÓN",
      "goliathScore": 60.0,
      "status": "warming",
      "confidence": 0.55,
      "riskLevel": "medium",
      "scoreReason": "Strong traction signals in AI.",
      "prediction": "BARCELONA SUPERCOMPUTING CENTER - CENTRO NACIONAL DE SUPERCOMPUTACIÓN is positioned to raise within 9 months.",
      "sector": "AI",
      "location": "Barcelona",
      "stage": null,
      "evidence": [
        {
          "id": "evd-ca3ec365",
          "source": "web",
          "title": "[PDF] Barcelona-&-Catalonia-Startup-Hub-2025 vdef a 260225_ENG",
          "url": "https://catalonia.com/documents/176177/179363/catalonia-trade-and-investment-analysis-of-the-startup-ecosystem-in-catalonia.pdf",
          "snippet": null
        },
        {
          "id": "evd-5630f236",
          "source": "web",
          "title": "The Barcelona Startup Ecosystem - Digital, Tech, and Open Innovation - Mind the Bridge",
          "url": "https://mindthebridge.com/2023-scaleups-barcelona",
          "snippet": null
        }
      ],
      "summary": "Ai in barcelona"
    },
    {
      "id": "opp-4",
      "startupName": "Sherpa.ai",
      "goliathScore": 60.0,
      "status": "warming",
      "confidence": 0.55,
      "riskLevel": "medium",
      "scoreReason": "Strong traction signals in AI.",
      "prediction": "Sherpa.ai is positioned to raise within 9 months.",
      "sector": "AI",
      "location": "Barcelona",
      "stage": null,
      "evidence": [
        {
          "id": "evd-c5564490",
          "source": "web",
          "title": "[PDF] Barcelona-&-Catalonia-Startup-Hub-2025 vdef a 260225_ENG",
          "url": "https://catalonia.com/documents/176177/179363/catalonia-trade-and-investment-analysis-of-the-startup-ecosystem-in-catalonia.pdf",
          "snippet": null
        },
        {
          "id": "evd-92aeeb01",
          "source": "web",
          "title": "The Barcelona Startup Ecosystem - Digital, Tech, and Open Innovation - Mind the Bridge",
          "url": "https://mindthebridge.com/2023-scaleups-barcelona",
          "snippet": null
        }
      ],
      "summary": "Ai in barcelona"
    }
  ],
  "segments": [
    {
      "id": "seg-fd6372c5",
      "agentId": "agent-0-market_mapper",
      "script": "The market is heating up. Demand signals point to real momentum, and ONLIVE LTD sits right at the center.",
      "subtitle": "The market is heating up. Demand signals point to real momentum, and ONLIVE LTD sits right at the center.",
      "audioUrl": "/api/audio/2b88d7aaa1a94d2a",
      "wordTimings": [],
      "imageUrl": null,
      "evidenceIds": [],
      "durationMs": null,
      "title": "Market Mapper"
    },
    {
      "id": "seg-3ff8eb22",
      "agentId": "agent-1-company_scout",
      "script": "Our top candidates are ONLIVE LTD, RISC-V International, Submer. ONLIVE LTD shows the strongest traction of the set.",
      "subtitle": "Our top candidates are ONLIVE LTD, RISC-V International, Submer. ONLIVE LTD shows the strongest traction of the set.",
      "audioUrl": "/api/audio/e981619e68554dd7",
      "wordTimings": [],
      "imageUrl": null,
      "evidenceIds": [],
      "durationMs": null,
      "title": "Company Scout"
    },
    {
      "id": "seg-1d96bd84",
      "agentId": "agent-2-current_opportunities",
      "script": "Our top candidates are ONLIVE LTD, RISC-V International, Submer. ONLIVE LTD shows the strongest traction of the set.",
      "subtitle": "Our top candidates are ONLIVE LTD, RISC-V International, Submer. ONLIVE LTD shows the strongest traction of the set.",
      "audioUrl": "/api/audio/af0e006d39b94bf5",
      "wordTimings": [],
      "imageUrl": null,
      "evidenceIds": [],
      "durationMs": null,
      "title": "Current Opportunities"
    },
    {
      "id": "seg-4c0c58b9",
      "agentId": "agent-3-funding_analyst",
      "script": "ONLIVE LTD looks primed for its next raise, likely within the next six to nine months.",
      "subtitle": "ONLIVE LTD looks primed for its next raise, likely within the next six to nine months.",
      "audioUrl": "/api/audio/5239f23bb0d2438f",
      "wordTimings": [],
      "imageUrl": null,
      "evidenceIds": [],
      "durationMs": null,
      "title": "Funding Analyst"
    }
  ],
  "id": "report-dump_213302",
  "title": "AI investment opportunities — Barcelona",
  "executiveSummary": "ONLIVE LTD leads at 60 (warming): Strong traction signals in AI. RISC-V International, Submer round out the shortlist."
}